autopeptideml/__init__.py
autopeptideml/apml.py
autopeptideml/main.py
autopeptideml/data/__init__.py
autopeptideml/data/chembl_monomer_library.xml
autopeptideml/data/result_analysis_c.qmd
autopeptideml/data/result_analysis_r.qmd
autopeptideml/data/h_param_search/catboost_class.yml
autopeptideml/data/h_param_search/catboost_reg.yml
autopeptideml/data/h_param_search/gradboost_class.yml
autopeptideml/data/h_param_search/gradboost_reg.yml
autopeptideml/data/h_param_search/knn_class.yml
autopeptideml/data/h_param_search/knn_reg.yml
autopeptideml/data/h_param_search/lightgbm_class.yml
autopeptideml/data/h_param_search/lightgbm_reg.yml
autopeptideml/data/h_param_search/logreg_class.yml
autopeptideml/data/h_param_search/rf_class.yml
autopeptideml/data/h_param_search/rf_reg.yml
autopeptideml/data/h_param_search/svm_class.yml
autopeptideml/data/h_param_search/svm_reg.yml
autopeptideml/data/h_param_search/xgboost_class.yml
autopeptideml/data/h_param_search/xgboost_reg.yml
autopeptideml/db/__init__.py
autopeptideml/db/negative_sampling.py
autopeptideml/pipeline/__init__.py
autopeptideml/pipeline/default_pipelines.py
autopeptideml/pipeline/pipeline.py
autopeptideml/pipeline/sequence.py
autopeptideml/pipeline/smiles.py
autopeptideml/reps/__init__.py
autopeptideml/reps/engine.py
autopeptideml/reps/fps.py
autopeptideml/reps/lms.py
autopeptideml/reps/seq_based.py
autopeptideml/reps/utils/__init__.py
autopeptideml/reps/utils/peptideclm_tokenizer.py
autopeptideml/train/__init__.py
autopeptideml/train/architectures.py
autopeptideml/train/metrics.py
autopeptideml/train/trainer.py
autopeptideml/train/deep_learning/__init__.py
autopeptideml/train/deep_learning/dataset.py
autopeptideml/train/deep_learning/loss.py
autopeptideml/train/deep_learning/model.py
autopeptideml/utils/__init__.py
autopeptideml/utils/config.py
autopeptideml/utils/dataset_parsing.py
autopeptideml/utils/label_balance.py
autopeptideml/utils/plots.py
autopeptideml/utils/yaml_format.py
autopeptideml-2.0.4.dist-info/licenses/LICENSE
autopeptideml-2.0.4.dist-info/METADATA
autopeptideml-2.0.4.dist-info/WHEEL
autopeptideml-2.0.4.dist-info/entry_points.txt
autopeptideml-2.0.4.dist-info/top_level.txt
autopeptideml-2.0.4.dist-info/RECORD
