Metadata-Version: 2.4
Name: autopeptideml
Version: 2.0.4
Summary: AutoML system for building trustworthy peptide bioactivity predictors
Home-page: https://ibm.github.io/AutoPeptideML/
Author: Raul Fernandez-Diaz
Author-email: raulfd@ibm.com
License: MIT
Keywords: autopeptideml
Requires-Python: >=3.9
License-File: LICENSE
Requires-Dist: optuna
Requires-Dist: scikit-learn
Requires-Dist: typer
Requires-Dist: tokenizers
Requires-Dist: torch
Requires-Dist: transformers
Requires-Dist: lightgbm
Requires-Dist: xgboost
Requires-Dist: seaborn
Requires-Dist: hestia-good
Requires-Dist: onnxmltools
Requires-Dist: skl2onnx
Requires-Dist: onnxruntime
Requires-Dist: rdkit
Requires-Dist: quarto
Requires-Dist: mapchiral
Requires-Dist: tabulate
Requires-Dist: ItsPrompt
Dynamic: author
Dynamic: author-email
Dynamic: description
Dynamic: description-content-type
Dynamic: home-page
Dynamic: keywords
Dynamic: license
Dynamic: license-file
Dynamic: requires-dist
Dynamic: requires-python
Dynamic: summary
